AnalyseSentiment/AnalyseSentiment.py
AnalyseSentiment/__init__.py
SentimentAnalysis-0.8.dist-info/LICENSE.txt
SentimentAnalysis-0.8.dist-info/METADATA
SentimentAnalysis-0.8.dist-info/WHEEL
SentimentAnalysis-0.8.dist-info/top_level.txt
SentimentAnalysis-0.8.dist-info/RECORD
